{"Questions":{"1":"1:**\n\nSolve the following:  (\u20133x\u00B2 \u002B 5x \u2013 7) \u002B (2x\u00B2 \u2013 8x \u002B 12)","2":"2:**\n\nFind the sum:  12.57 \u002B 3.041 \u002B 0.9","3":"3:**\n\nAdd the following complex numbers: (3 \u002B 2i) \u002B (\u20131 \u2013 5i)","4":"4:**\n\nA rectangular garden has sides of length (3x \u002B 2) meters and (x \u2013 5) meters.  What is the expression for the perimeter of the garden?","5":"5:**\n\nSimplify the following expression:  (2a \u002B 3b) \u002B (5a \u2013 b) \u002B (\u2013a \u002B 7b)"},"Choices":{"1":["a) \u2013x\u00B2 \u2013 3x \u002B 5","b) \u20135x\u00B2 \u002B 13x \u2013 19","c) 5x\u00B2 \u002B 13x \u002B 5","d) \u2013x\u00B2 \u002B 13x \u002B 5"],"2":["a) 15.511","b) 16.511","c) 15.411","d) 17.511"],"3":["a) 2 \u2013 3i","b) 4 \u2013 3i","c) 2 \u002B 7i","d) 4 \u002B 7i"],"4":["a) 4x - 3 meters","b) 8x - 6 meters","c) 3x\u00B2 - 13x -10 meters","d) 4x \u002B 14 meters"],"5":["a) 6a \u002B 9b","b) 6a \u002B 7b","c) 5a \u002B 9b","d) 8a \u002B 9b"]}}